flake8-stubs/METADATA.toml
flake8-stubs/__init__.pyi
flake8-stubs/_compat.pyi
flake8-stubs/checker.pyi
flake8-stubs/defaults.pyi
flake8-stubs/discover_files.pyi
flake8-stubs/exceptions.pyi
flake8-stubs/processor.pyi
flake8-stubs/py.typed
flake8-stubs/statistics.pyi
flake8-stubs/style_guide.pyi
flake8-stubs/utils.pyi
flake8-stubs/violation.pyi
flake8-stubs/api/__init__.pyi
flake8-stubs/api/legacy.pyi
flake8-stubs/formatting/__init__.pyi
flake8-stubs/formatting/_windows_color.pyi
flake8-stubs/formatting/base.pyi
flake8-stubs/formatting/default.pyi
flake8-stubs/main/__init__.pyi
flake8-stubs/main/application.pyi
flake8-stubs/main/cli.pyi
flake8-stubs/main/debug.pyi
flake8-stubs/main/options.pyi
flake8-stubs/options/__init__.pyi
flake8-stubs/options/aggregator.pyi
flake8-stubs/options/config.pyi
flake8-stubs/options/manager.pyi
flake8-stubs/options/parse_args.pyi
flake8-stubs/plugins/__init__.pyi
flake8-stubs/plugins/finder.pyi
flake8-stubs/plugins/pycodestyle.pyi
flake8-stubs/plugins/pyflakes.pyi
flake8-stubs/plugins/reporter.pyi
types_flake8-7.2.0.20250330.dist-info/licenses/LICENSE
types_flake8-7.2.0.20250330.dist-info/METADATA
types_flake8-7.2.0.20250330.dist-info/WHEEL
types_flake8-7.2.0.20250330.dist-info/top_level.txt
types_flake8-7.2.0.20250330.dist-info/RECORD
